pytest_diamond.py
pytest_diamond-0.0.1.dist-info/DESCRIPTION.rst
pytest_diamond-0.0.1.dist-info/entry_points.txt
pytest_diamond-0.0.1.dist-info/METADATA
pytest_diamond-0.0.1.dist-info/metadata.json
pytest_diamond-0.0.1.dist-info/pbr.json
pytest_diamond-0.0.1.dist-info/RECORD
pytest_diamond-0.0.1.dist-info/top_level.txt
pytest_diamond-0.0.1.dist-info/WHEEL
