Metadata-Version: 2.0
Name: pytest-diamond
Version: 0.0.1
Summary: pytest plugin for diamond
Home-page: https://github.com/python-diamond/pytest-diamond
Author: Matt Robenolt
Author-email: matt@ydekproductions.com
License: MIT
Platform: UNKNOWN
Classifier: Development Status :: 4 - Beta
Classifier: Intended Audience :: Developers
Classifier: Topic :: Software Development :: Testing
Classifier: Programming Language :: Python
Classifier: Operating System :: OS Independent
Classifier: License :: OSI Approved :: MIT License
Requires-Dist: pytest (>=2.7.2)
